renpy/ast.py
renpy/astsupport.py
renpy/atl.py
renpy/config.py
renpy/lexer.py
renpy/object.py
renpy/pyanalysis.py
renpy/python.py
renpy/revertable.py
renpy/script.py
renpy/ui.py
renpy/util.py
renpy/display/behavior.py
renpy/display/core.py
renpy/display/dragdrop.py
renpy/display/layout.py
renpy/display/transform.py
renpy/parameter/__init__.py
renpy/sl2/slast.py
renpy/sl2/sldisplayables.py
renpy/test/__init__.py
renpy/text/extras.py
renpy/text/font.py
renpy/text/text.py
renpy/translation/__init__.py
renpy/translation/generation.py
renpy/translation/scanstrings.py
rpycdec/__init__.py
rpycdec/__main__.py
rpycdec/cli.py
rpycdec/decompile.py
rpycdec/rpa.py
rpycdec/save.py
rpycdec/stmts.py
rpycdec/translate.py
rpycdec/utils.py
store/__init__.py
store/layeredimage.py
rpycdec-0.1.9.dist-info/METADATA
rpycdec-0.1.9.dist-info/WHEEL
rpycdec-0.1.9.dist-info/entry_points.txt
rpycdec-0.1.9.dist-info/licenses/LICENSE
rpycdec-0.1.9.dist-info/RECORD
