Metadata-Version: 2.4
Name: rpycdec
Version: 0.1.9
Summary: A tool to decrypt .rpyc files
Project-URL: Homepage, https://github.com/cnfatal/rpycdec
Project-URL: Bug Tracker, https://github.com/cnfatal/rpycdec/issues
Author-email: cnfatal <cnfatal@gmail.com>
License-File: LICENSE
Classifier: License :: OSI Approved :: MIT License
Classifier: Operating System :: OS Independent
Classifier: Programming Language :: Python :: 3
Classifier: Topic :: Utilities
Requires-Python: >=3.10
Requires-Dist: ratelimit
Requires-Dist: requests
Requires-Dist: tqdm
Provides-Extra: release
Requires-Dist: twine; extra == 'release'
Provides-Extra: transformers
Requires-Dist: sentencepiece; extra == 'transformers'
Requires-Dist: torch; extra == 'transformers'
Requires-Dist: transformers; extra == 'transformers'
